LICENSE.md
setup.py
ask_the_duck/__init__.py
ask_the_duck/api.py
ask_the_duck/session.py
ask_the_duck/util.py
ask_the_duck.egg-info/PKG-INFO
ask_the_duck.egg-info/SOURCES.txt
ask_the_duck.egg-info/dependency_links.txt
ask_the_duck.egg-info/requires.txt
ask_the_duck.egg-info/top_level.txt