Metadata-Version: 1.0
Name: ask-the-duck
Version: 0.0.1
Summary: duck duck go library
Home-page: https://github.com/HelloChatterbox/ask-the-duck
Author: jarbasAi
Author-email: jarbasai@mailfence.com
License: apache-2.0
Platform: UNKNOWN
